wxapi/__init__.py
wxapi/zabbix-wx-alert.py
zabbix_weixin_alert-2019.2.27.5.dist-info/LICENSE
zabbix_weixin_alert-2019.2.27.5.dist-info/METADATA
zabbix_weixin_alert-2019.2.27.5.dist-info/WHEEL
zabbix_weixin_alert-2019.2.27.5.dist-info/top_level.txt
zabbix_weixin_alert-2019.2.27.5.dist-info/RECORD
